<Texts Type="Other">
	<List>
		<Text Name="God_Gong_1">
			<DisplayName>Sutra da Salvação do Trovão Celestial</DisplayName>
			<Desc>Um método de cultivo da Lei de Shendao que se perdeu desde os tempos antigos, é uma forma de reunir a fé dos seres vivos para alcançar a divindade. A maioria das escolas da Lei de Shendao compartilham muitas semelhanças, elas diferem apenas no tipo de catalisador espiritual usado, que convoca diferentes seres celestiais para proteção. A Escritura do Mestre do Trovão Celestial é o legado do Mestre do Trovão. Ao cultivar esse método, seria possível aproveitar o catalisador espiritual do Mestre do Trovão para convocar os muitos espíritos do trovão dos Céus como guardiões. Ele enfatiza o domínio do artefato e o ataque.</Desc>
			<SelectDesc>O Cultivo da Fé é diferente da forma mais tradicional de utilizar o Núcleo Dourado. Depende inteiramente da fé dos seres viventes. Embora não haja exigência de talento para o cultivo da fé, você ainda precisa ter um nível muito alto de inteligência se quiser chegar ao topo. Você deseja escolher cultivar esta Lei?</SelectDesc>
			<Stages.0.DisplayName>Asceta</Stages.0.DisplayName>
			<Stages.0.Necks.0.DisplayName>Devoção</Stages.0.Necks.0.DisplayName>
			<Stages.1.DisplayName>Pregação</Stages.1.DisplayName>
			<Stages.1.Necks.0.DisplayName>Criação</Stages.1.Necks.0.DisplayName>
			<Stages.2.DisplayName>Condutores</Stages.2.DisplayName>
			<Stages.2.Necks.0.DisplayName>Decreto: Condutores</Stages.2.Necks.0.DisplayName>
			<Stages.3.DisplayName>Trovão</Stages.3.DisplayName>
			<Stages.3.Necks.0.DisplayName>Decreto: Trovão</Stages.3.Necks.0.DisplayName>
			<Stages.4.DisplayName>Yin Yang</Stages.4.DisplayName>
			<Stages.4.Necks.0.DisplayName>Decreto: Yin Yang</Stages.4.Necks.0.DisplayName>
			<Stages.4.Necks.1.DisplayName>Transcendência</Stages.4.Necks.1.DisplayName>
			<Stages.5.DisplayName>Conquista</Stages.5.DisplayName>
			<Stages.5.Necks.0.DisplayName>Supremo</Stages.5.Necks.0.DisplayName>
		</Text>
	</List>
</Texts>